{
  "slug": "entryway-shoe-cabinet-umbrella-bag-cleaning-tools",
  "category": "lifestyle-culture",
  "topicCategory": "home-rituals",
  "topicCategoryLabel": "居家儀式",
  "primaryHub": {
    "key": "mature-life-reset",
    "title": "人生重整與一人生活秩序",
    "file": "mature-life-reset.html",
    "url": "/mature-life-reset",
    "category": "lifestyle-culture"
  },
  "secondaryHubs": [
    {
      "key": "commute-style-reset",
      "title": "通勤衣櫥與鞋包選物指南",
      "file": "commute-style-reset.html",
      "url": "/commute-style-reset",
      "category": "casual-chic"
    }
  ],
  "title": "玄關不是倉庫：鞋櫃、傘架、外出包與清潔工具怎麼分工",
  "excerpt": "玄關分工要先看鞋櫃容量、傘具濕物、外出包暫放與清潔工具位置，再比較家具與收納品。",
  "tags": [
    "玄關收納",
    "鞋櫃傘架",
    "外出包",
    "清潔工具"
  ],
  "metaTitle": "Elite Fashion｜玄關不是倉庫：鞋櫃、傘架、外出包與清潔工具怎麼分工",
  "metaDescription": "玄關分工要先看鞋櫃容量、傘具濕物、外出包暫放與清潔工具位置，再比較家具與收納品。 本文整理選購順序、常見錯誤與下單前確認重點。",
  "series": "城市生活選物",
  "listingTitle": "玄關不是倉庫：鞋櫃、傘架、外出包與清潔工具怎麼分工",
  "listingExcerpt": "玄關分工要先看鞋櫃容量、傘具濕物、外出包暫放與清潔工具位置，再比較家具與收納品。",
  "heroImage": "/images/optimized/article-covers/entryway-shoe-cabinet-umbrella-bag-cleaning-tools.jpg",
  "heroImageAlt": "現代玄關有鞋櫃、傘架、無品牌外出包、清潔工具收納架、掛鉤、鏡子與植栽",
  "coverImageStatus": "codex-generated",
  "intro": "玄關最容易從過渡空間變成倉庫。鞋櫃、傘架、外出包、清潔工具和家具若沒有分工，每天出門與回家都會被同一堆東西攔住。玄關要先處理四件事：出門、回家、濕物、清潔。台灣雨季和通勤節奏讓玄關很容易累積傘、鞋、包與地面灰塵，所以分工比容量更重要。真正好用的玄關，不是把所有東西藏起來，而是讓今天會用的物件留在手邊，其他物件退到櫃內或下一層。",
  "sections": [
    {
      "heading": "鞋櫃先看容量和換鞋動線",
      "paragraphs": [
        "鞋櫃不是只收鞋，也要讓出門前能順手換鞋。",
        "完美主義、悅家傢具城與 RED HOUSE 可放在家具收納裡比較。",
        "Elite Fashion 編輯團隊的具體判斷是：玄關先分出門、回家、濕物與清潔四件事，不要讓鞋櫃、傘架、包款和工具互相搶位置。 這讓 完美主義 官方直營、真蓁嚴選清潔生活館-專賣平板拖把、掃把、掃除用品 與其他選項能被放回同一個生活問題裡比較，而不是只看單一商品照片。",
        "下單前仍要回商品頁確認規格、尺寸、材質、活動、庫存與配送；若資訊不足，先暫緩，比把不確定的物品帶回家更成熟。"
      ],
      "bullets": [
        "先確認使用位置與拿取頻率。",
        "再看保存、清潔、線材或收納條件。",
        "最後才比較品牌、活動與預算。"
      ]
    },
    {
      "heading": "傘架要處理濕物",
      "paragraphs": [
        "傘具若沒有滴水和晾乾位置，玄關很快會潮濕混亂。",
        "FULTON 可作為晴雨傘備案參考。",
        "Elite Fashion 編輯團隊的具體判斷是：玄關先分出門、回家、濕物與清潔四件事，不要讓鞋櫃、傘架、包款和工具互相搶位置。 這讓 完美主義 官方直營、真蓁嚴選清潔生活館-專賣平板拖把、掃把、掃除用品 與其他選項能被放回同一個生活問題裡比較，而不是只看單一商品照片。",
        "下單前仍要回商品頁確認規格、尺寸、材質、活動、庫存與配送；若資訊不足，先暫緩，比把不確定的物品帶回家更成熟。"
      ],
      "bullets": [
        "先確認使用位置與拿取頻率。",
        "再看保存、清潔、線材或收納條件。",
        "最後才比較品牌、活動與預算。"
      ]
    },
    {
      "heading": "包款只放今日外出",
      "paragraphs": [
        "S′AIME 可作為外出包參考，但玄關不該堆放所有包。",
        "包款尺寸、材質與收納方式請以商品頁為準。",
        "Elite Fashion 編輯團隊的具體判斷是：玄關先分出門、回家、濕物與清潔四件事，不要讓鞋櫃、傘架、包款和工具互相搶位置。 這讓 完美主義 官方直營、真蓁嚴選清潔生活館-專賣平板拖把、掃把、掃除用品 與其他選項能被放回同一個生活問題裡比較，而不是只看單一商品照片。",
        "下單前仍要回商品頁確認規格、尺寸、材質、活動、庫存與配送；若資訊不足，先暫緩，比把不確定的物品帶回家更成熟。"
      ],
      "bullets": [
        "先確認使用位置與拿取頻率。",
        "再看保存、清潔、線材或收納條件。",
        "最後才比較品牌、活動與預算。"
      ]
    },
    {
      "heading": "常見錯誤：清潔工具沒有家",
      "paragraphs": [
        "掃把、拖把、擦拭布若放在視線外，回家後的小髒污就會被拖延。",
        "真蓁嚴選可作為清潔工具參考。",
        "Elite Fashion 編輯團隊的具體判斷是：玄關先分出門、回家、濕物與清潔四件事，不要讓鞋櫃、傘架、包款和工具互相搶位置。 這讓 完美主義 官方直營、真蓁嚴選清潔生活館-專賣平板拖把、掃把、掃除用品 與其他選項能被放回同一個生活問題裡比較，而不是只看單一商品照片。",
        "下單前仍要回商品頁確認規格、尺寸、材質、活動、庫存與配送；若資訊不足，先暫緩，比把不確定的物品帶回家更成熟。"
      ],
      "bullets": [
        "先確認使用位置與拿取頻率。",
        "再看保存、清潔、線材或收納條件。",
        "最後才比較品牌、活動與預算。"
      ]
    },
    {
      "heading": "下單前畫四區",
      "paragraphs": [
        "鞋、傘、包、清潔。每區只能放最常用的物件；如果同一區超過三種用途，就代表需要分層、移位或減少品項。",
        "價格、尺寸、材質、承重與庫存請以下單前商品頁公告為準。Elite Fashion 編輯團隊的判斷是：玄關的轉單價值在於讓讀者看見缺的是鞋櫃、傘架、包款暫放還是清潔工具，而不是一次買滿家具。",
        "Elite Fashion 編輯團隊的具體判斷是：玄關先分出門、回家、濕物與清潔四件事，不要讓鞋櫃、傘架、包款和工具互相搶位置。 這讓 完美主義 官方直營、真蓁嚴選清潔生活館-專賣平板拖把、掃把、掃除用品 與其他選項能被放回同一個生活問題裡比較，而不是只看單一商品照片。",
        "下單前仍要回商品頁確認規格、尺寸、材質、活動、庫存與配送；若資訊不足，先暫緩，比把不確定的物品帶回家更成熟。"
      ],
      "bullets": [
        "先確認使用位置與拿取頻率。",
        "再看保存、清潔、線材或收納條件。",
        "最後才比較品牌、活動與預算。"
      ]
    }
  ],
  "faq": [
    {
      "question": "玄關第一步整理什麼？",
      "answer": "先分鞋、傘、包、清潔四區。"
    },
    {
      "question": "鞋櫃越大越好嗎？",
      "answer": "不一定，要看換鞋動線和常穿鞋數量。"
    },
    {
      "question": "清潔工具可以藏起來嗎？",
      "answer": "可以，但要拿得到，否則很難維持。"
    }
  ],
  "extendedReading": [
    {
      "title": "瀏覽更多生活品味文章",
      "url": "/lifestyle-culture.html"
    },
    {
      "title": "瀏覽所有文章",
      "url": "/all-articles.html"
    },
    {
      "title": "查看站內搜尋",
      "url": "/search.html"
    }
  ],
  "cta": {
    "variant": "olive",
    "text": "玄關分工要先看鞋櫃容量、傘具濕物、外出包暫放與清潔工具位置，再比較家具與收納品。 先用本文順序縮小範圍，再回商品頁確認規格、價格、活動與庫存。",
    "links": [
      {
        "label": "查看 完美主義 官方直營",
        "url": "https://s.momoshop.com.tw/s/4sSbnDHc"
      },
      {
        "label": "查看 真蓁嚴選清潔生活館-專賣平板拖把、掃把、掃除用品",
        "url": "https://s.momoshop.com.tw/s/NaHe80dq"
      },
      {
        "label": "查看 悅家傢具城",
        "url": "https://s.momoshop.com.tw/s/HnjPEoa8"
      },
      {
        "label": "查看 RED HOUSE 家具工廠",
        "url": "https://s.momoshop.com.tw/s/5ME3fNxI"
      }
    ]
  },
  "inlineCtas": [
    {
      "afterSection": 2,
      "variant": "gold",
      "eyebrow": "編輯精選",
      "heading": "先把最常發生的情境排出來",
      "text": "玄關不是倉庫，而是出入門系統。",
      "links": [
        {
          "label": "完美主義 官方直營 選物頁",
          "url": "https://s.momoshop.com.tw/s/4sSbnDHc"
        },
        {
          "label": "真蓁嚴選清潔生活館-專賣平板拖把、掃把、掃除用品 選物頁",
          "url": "https://s.momoshop.com.tw/s/NaHe80dq"
        }
      ]
    },
    {
      "afterSection": 4,
      "variant": "olive",
      "eyebrow": "下單前確認",
      "heading": "商品頁資訊是最後一道檢查",
      "text": "鞋櫃、傘架、家具、包款與清潔工具的尺寸、材質、承重、保養與使用限制請以商品頁及包裝為準。",
      "links": [
        {
          "label": "悅家傢具城 選物頁",
          "url": "https://s.momoshop.com.tw/s/HnjPEoa8"
        },
        {
          "label": "RED HOUSE 家具工廠 選物頁",
          "url": "https://s.momoshop.com.tw/s/5ME3fNxI"
        }
      ]
    }
  ],
  "disclaimer": "本文含品牌／商品導購連結；商品資訊、價格、規格、活動與庫存請以商品頁公告為準。鞋櫃、傘架、家具、包款與清潔工具的尺寸、材質、承重、保養與使用限制請以商品頁及包裝為準。",
  "audience": "想讓玄關從暫放區變成出入門系統的人",
  "readTimeMinutes": 10,
  "sourceType": "manual-codex-momo-revenue-growth-batch-twelve-no-newsletter",
  "status": "published",
  "queueId": "MOMO-REV-2026-06-21-W01-B12",
  "mainProducts": [
    {
      "name": "完美主義 官方直營 選物頁",
      "merchantId": "TP0005953",
      "brandName": "完美主義 官方直營",
      "affiliateUrl": "https://s.momoshop.com.tw/s/4sSbnDHc",
      "sourceProductUrl": "https://www.momoshop.com.tw/TP/TP0005953/main",
      "imageCredit": "圖片來源：momo 店家頁｜完美主義 官方直營",
      "selectionReason": "租屋族、小家庭、新居裝潢族、收納需求者。下單前請回到商品頁確認尺寸、材質、規格、活動與即時販售資訊。",
      "riskNote": "價格、規格、活動、庫存與配送條件請以下單前商品頁公告為準。",
      "subId": "entryway-shoe-cabinet-umbrella-bag-cleaning-tools_TP0005953"
    },
    {
      "name": "真蓁嚴選清潔生活館-專賣平板拖把、掃把、掃除用品 選物頁",
      "merchantId": "TP0000922",
      "brandName": "真蓁嚴選清潔生活館-專賣平板拖把、掃把、掃除用品",
      "affiliateUrl": "https://s.momoshop.com.tw/s/NaHe80dq",
      "sourceProductUrl": "https://www.momoshop.com.tw/TP/TP0000922/main",
      "imageCredit": "圖片來源：momo 店家頁｜真蓁嚴選清潔生活館-專賣平板拖把、掃把、掃除用品",
      "selectionReason": "平板拖把怎麼選、掃除工具清單、租屋清潔必備。下單前請回到商品頁確認尺寸、材質、規格、活動與即時販售資訊。",
      "riskNote": "價格、規格、活動、庫存與配送條件請以下單前商品頁公告為準。",
      "subId": "entryway-shoe-cabinet-umbrella-bag-cleaning-tools_TP0000922"
    },
    {
      "name": "悅家傢具城 選物頁",
      "merchantId": "TP0006481",
      "brandName": "悅家傢具城",
      "affiliateUrl": "https://s.momoshop.com.tw/s/HnjPEoa8",
      "sourceProductUrl": "https://www.momoshop.com.tw/TP/TP0006481/main",
      "imageCredit": "圖片來源：momo 店家頁｜悅家傢具城",
      "selectionReason": "商品清單、尺寸動線、使用頻率、收納與送禮情境。下單前請回到商品頁確認尺寸、材質、規格、活動與即時販售資訊。",
      "riskNote": "價格、規格、活動、庫存與配送條件請以下單前商品頁公告為準。",
      "subId": "entryway-shoe-cabinet-umbrella-bag-cleaning-tools_TP0006481"
    },
    {
      "name": "RED HOUSE 家具工廠 選物頁",
      "merchantId": "TP0007407",
      "brandName": "RED HOUSE 家具工廠",
      "affiliateUrl": "https://s.momoshop.com.tw/s/5ME3fNxI",
      "sourceProductUrl": "https://www.momoshop.com.tw/TP/TP0007407/main",
      "imageCredit": "圖片來源：momo 店家頁｜RED HOUSE 家具工廠",
      "selectionReason": "商品清單、尺寸動線、使用頻率、收納與送禮情境。下單前請回到商品頁確認尺寸、材質、規格、活動與即時販售資訊。",
      "riskNote": "價格、規格、活動、庫存與配送條件請以下單前商品頁公告為準。",
      "subId": "entryway-shoe-cabinet-umbrella-bag-cleaning-tools_TP0007407"
    }
  ],
  "sidebarProducts": [
    {
      "name": "FULTON 富爾頓皇家晴雨傘 選物頁",
      "merchantId": "TP0005684",
      "brandName": "FULTON 富爾頓皇家晴雨傘",
      "affiliateUrl": "https://s.momoshop.com.tw/s/swCkSJDA",
      "sourceProductUrl": "https://www.momoshop.com.tw/TP/TP0005684/main",
      "imageCredit": "圖片來源：momo 店家頁｜FULTON 富爾頓皇家晴雨傘",
      "selectionReason": "抗風傘比較、通勤傘推薦、旅行雨具、英倫風格配件。下單前請回到商品頁確認尺寸、材質、規格、活動與即時販售資訊。",
      "riskNote": "價格、規格、活動、庫存與配送條件請以下單前商品頁公告為準。",
      "subId": "entryway-shoe-cabinet-umbrella-bag-cleaning-tools_TP0005684"
    },
    {
      "name": "S′AIME東京企劃 選物頁",
      "merchantId": "TP0007070",
      "brandName": "S′AIME東京企劃",
      "affiliateUrl": "https://s.momoshop.com.tw/s/fZ9miz2D",
      "sourceProductUrl": "https://www.momoshop.com.tw/TP/TP0007070/main",
      "imageCredit": "圖片來源：momo 店家頁｜S′AIME東京企劃",
      "selectionReason": "商品清單、尺寸動線、使用頻率、收納與送禮情境。下單前請回到商品頁確認尺寸、材質、規格、活動與即時販售資訊。",
      "riskNote": "價格、規格、活動、庫存與配送條件請以下單前商品頁公告為準。",
      "subId": "entryway-shoe-cabinet-umbrella-bag-cleaning-tools_TP0007070"
    }
  ],
  "featuredBrands": [
    {
      "name": "完美主義 官方直營",
      "merchantId": "TP0005953",
      "role": "情境比較",
      "reason": "租屋族、小家庭、新居裝潢族、收納需求者",
      "url": "https://s.momoshop.com.tw/s/4sSbnDHc"
    },
    {
      "name": "真蓁嚴選清潔生活館-專賣平板拖把、掃把、掃除用品",
      "merchantId": "TP0000922",
      "role": "情境比較",
      "reason": "平板拖把怎麼選、掃除工具清單、租屋清潔必備",
      "url": "https://s.momoshop.com.tw/s/NaHe80dq"
    },
    {
      "name": "悅家傢具城",
      "merchantId": "TP0006481",
      "role": "情境比較",
      "reason": "商品清單、尺寸動線、使用頻率、收納與送禮情境",
      "url": "https://s.momoshop.com.tw/s/HnjPEoa8"
    },
    {
      "name": "RED HOUSE 家具工廠",
      "merchantId": "TP0007407",
      "role": "情境比較",
      "reason": "商品清單、尺寸動線、使用頻率、收納與送禮情境",
      "url": "https://s.momoshop.com.tw/s/5ME3fNxI"
    },
    {
      "name": "FULTON 富爾頓皇家晴雨傘",
      "merchantId": "TP0005684",
      "role": "情境比較",
      "reason": "抗風傘比較、通勤傘推薦、旅行雨具、英倫風格配件",
      "url": "https://s.momoshop.com.tw/s/swCkSJDA"
    },
    {
      "name": "S′AIME東京企劃",
      "merchantId": "TP0007070",
      "role": "情境比較",
      "reason": "商品清單、尺寸動線、使用頻率、收納與送禮情境",
      "url": "https://s.momoshop.com.tw/s/fZ9miz2D"
    }
  ],
  "id": "auto-20260621123703-entryway-shoe-cabinet-umbrella-bag-cleaning-tools",
  "publishedAt": "2026-06-21T12:37:03Z",
  "publishedDateText": "2026年6月21日",
  "url": "https://tw.elitefasion.com/lifestyle-culture/entryway-shoe-cabinet-umbrella-bag-cleaning-tools",
  "file": "lifestyle-culture/entryway-shoe-cabinet-umbrella-bag-cleaning-tools.html",
  "relativeUrl": "lifestyle-culture/entryway-shoe-cabinet-umbrella-bag-cleaning-tools.html",
  "markdownBody": "# 玄關不是倉庫：鞋櫃、傘架、外出包與清潔工具怎麼分工\n\n玄關最容易從過渡空間變成倉庫。鞋櫃、傘架、外出包、清潔工具和家具若沒有分工，每天出門與回家都會被同一堆東西攔住。玄關要先處理四件事：出門、回家、濕物、清潔。台灣雨季和通勤節奏讓玄關很容易累積傘、鞋、包與地面灰塵，所以分工比容量更重要。真正好用的玄關，不是把所有東西藏起來，而是讓今天會用的物件留在手邊，其他物件退到櫃內或下一層。\n\n## 鞋櫃先看容量和換鞋動線\n\n鞋櫃不是只收鞋，也要讓出門前能順手換鞋。\n\n完美主義、悅家傢具城與 RED HOUSE 可放在家具收納裡比較。\n\nElite Fashion 編輯團隊的具體判斷是：玄關先分出門、回家、濕物與清潔四件事，不要讓鞋櫃、傘架、包款和工具互相搶位置。 這讓 完美主義 官方直營、真蓁嚴選清潔生活館-專賣平板拖把、掃把、掃除用品 與其他選項能被放回同一個生活問題裡比較，而不是只看單一商品照片。\n\n下單前仍要回商品頁確認規格、尺寸、材質、活動、庫存與配送；若資訊不足，先暫緩，比把不確定的物品帶回家更成熟。\n\n- 先確認使用位置與拿取頻率。\n- 再看保存、清潔、線材或收納條件。\n- 最後才比較品牌、活動與預算。\n\n## 傘架要處理濕物\n\n傘具若沒有滴水和晾乾位置，玄關很快會潮濕混亂。\n\nFULTON 可作為晴雨傘備案參考。\n\nElite Fashion 編輯團隊的具體判斷是：玄關先分出門、回家、濕物與清潔四件事，不要讓鞋櫃、傘架、包款和工具互相搶位置。 這讓 完美主義 官方直營、真蓁嚴選清潔生活館-專賣平板拖把、掃把、掃除用品 與其他選項能被放回同一個生活問題裡比較，而不是只看單一商品照片。\n\n下單前仍要回商品頁確認規格、尺寸、材質、活動、庫存與配送；若資訊不足，先暫緩，比把不確定的物品帶回家更成熟。\n\n- 先確認使用位置與拿取頻率。\n- 再看保存、清潔、線材或收納條件。\n- 最後才比較品牌、活動與預算。\n\n## 先把最常發生的情境排出來\n\n玄關不是倉庫，而是出入門系統。\n\n- [完美主義 官方直營 選物頁](https://s.momoshop.com.tw/s/4sSbnDHc)\n- [真蓁嚴選清潔生活館-專賣平板拖把、掃把、掃除用品 選物頁](https://s.momoshop.com.tw/s/NaHe80dq)\n\n## 包款只放今日外出\n\nS′AIME 可作為外出包參考，但玄關不該堆放所有包。\n\n包款尺寸、材質與收納方式請以商品頁為準。\n\nElite Fashion 編輯團隊的具體判斷是：玄關先分出門、回家、濕物與清潔四件事，不要讓鞋櫃、傘架、包款和工具互相搶位置。 這讓 完美主義 官方直營、真蓁嚴選清潔生活館-專賣平板拖把、掃把、掃除用品 與其他選項能被放回同一個生活問題裡比較，而不是只看單一商品照片。\n\n下單前仍要回商品頁確認規格、尺寸、材質、活動、庫存與配送；若資訊不足，先暫緩，比把不確定的物品帶回家更成熟。\n\n- 先確認使用位置與拿取頻率。\n- 再看保存、清潔、線材或收納條件。\n- 最後才比較品牌、活動與預算。\n\n## 常見錯誤：清潔工具沒有家\n\n掃把、拖把、擦拭布若放在視線外，回家後的小髒污就會被拖延。\n\n真蓁嚴選可作為清潔工具參考。\n\nElite Fashion 編輯團隊的具體判斷是：玄關先分出門、回家、濕物與清潔四件事，不要讓鞋櫃、傘架、包款和工具互相搶位置。 這讓 完美主義 官方直營、真蓁嚴選清潔生活館-專賣平板拖把、掃把、掃除用品 與其他選項能被放回同一個生活問題裡比較，而不是只看單一商品照片。\n\n下單前仍要回商品頁確認規格、尺寸、材質、活動、庫存與配送；若資訊不足，先暫緩，比把不確定的物品帶回家更成熟。\n\n- 先確認使用位置與拿取頻率。\n- 再看保存、清潔、線材或收納條件。\n- 最後才比較品牌、活動與預算。\n\n## 商品頁資訊是最後一道檢查\n\n鞋櫃、傘架、家具、包款與清潔工具的尺寸、材質、承重、保養與使用限制請以商品頁及包裝為準。\n\n- [悅家傢具城 選物頁](https://s.momoshop.com.tw/s/HnjPEoa8)\n- [RED HOUSE 家具工廠 選物頁](https://s.momoshop.com.tw/s/5ME3fNxI)\n\n## 下單前畫四區\n\n鞋、傘、包、清潔。每區只能放最常用的物件；如果同一區超過三種用途，就代表需要分層、移位或減少品項。\n\n價格、尺寸、材質、承重與庫存請以下單前商品頁公告為準。Elite Fashion 編輯團隊的判斷是：玄關的轉單價值在於讓讀者看見缺的是鞋櫃、傘架、包款暫放還是清潔工具，而不是一次買滿家具。\n\nElite Fashion 編輯團隊的具體判斷是：玄關先分出門、回家、濕物與清潔四件事，不要讓鞋櫃、傘架、包款和工具互相搶位置。 這讓 完美主義 官方直營、真蓁嚴選清潔生活館-專賣平板拖把、掃把、掃除用品 與其他選項能被放回同一個生活問題裡比較，而不是只看單一商品照片。\n\n下單前仍要回商品頁確認規格、尺寸、材質、活動、庫存與配送；若資訊不足，先暫緩，比把不確定的物品帶回家更成熟。\n\n- 先確認使用位置與拿取頻率。\n- 再看保存、清潔、線材或收納條件。\n- 最後才比較品牌、活動與預算。\n\n## FAQ\n\n### 玄關第一步整理什麼？\n\n先分鞋、傘、包、清潔四區。\n\n### 鞋櫃越大越好嗎？\n\n不一定，要看換鞋動線和常穿鞋數量。\n\n### 清潔工具可以藏起來嗎？\n\n可以，但要拿得到，否則很難維持。\n\n## 延伸閱讀\n\n- [瀏覽更多生活品味文章](/lifestyle-culture.html)\n- [瀏覽所有文章](/all-articles.html)\n- [查看站內搜尋](/search.html)\n\n## CTA\n\n玄關分工要先看鞋櫃容量、傘具濕物、外出包暫放與清潔工具位置，再比較家具與收納品。 先用本文順序縮小範圍，再回商品頁確認規格、價格、活動與庫存。\n\n- [查看 完美主義 官方直營](https://s.momoshop.com.tw/s/4sSbnDHc)\n- [查看 真蓁嚴選清潔生活館-專賣平板拖把、掃把、掃除用品](https://s.momoshop.com.tw/s/NaHe80dq)\n- [查看 悅家傢具城](https://s.momoshop.com.tw/s/HnjPEoa8)\n- [查看 RED HOUSE 家具工廠](https://s.momoshop.com.tw/s/5ME3fNxI)\n\n## 重要警語\n\n本文含品牌／商品導購連結；商品資訊、價格、規格、活動與庫存請以商品頁公告為準。鞋櫃、傘架、家具、包款與清潔工具的尺寸、材質、承重、保養與使用限制請以商品頁及包裝為準。\n\n## Elite 嚴選\n\n- [完美主義 官方直營 選物頁](https://s.momoshop.com.tw/s/4sSbnDHc)：租屋族、小家庭、新居裝潢族、收納需求者。下單前請回到商品頁確認尺寸、材質、規格、活動與即時販售資訊。\n- [真蓁嚴選清潔生活館-專賣平板拖把、掃把、掃除用品 選物頁](https://s.momoshop.com.tw/s/NaHe80dq)：平板拖把怎麼選、掃除工具清單、租屋清潔必備。下單前請回到商品頁確認尺寸、材質、規格、活動與即時販售資訊。\n- [悅家傢具城 選物頁](https://s.momoshop.com.tw/s/HnjPEoa8)：商品清單、尺寸動線、使用頻率、收納與送禮情境。下單前請回到商品頁確認尺寸、材質、規格、活動與即時販售資訊。\n- [RED HOUSE 家具工廠 選物頁](https://s.momoshop.com.tw/s/5ME3fNxI)：商品清單、尺寸動線、使用頻率、收納與送禮情境。下單前請回到商品頁確認尺寸、材質、規格、活動與即時販售資訊。\n\n## 同主題品牌參考\n\n- [完美主義 官方直營](https://s.momoshop.com.tw/s/4sSbnDHc)：租屋族、小家庭、新居裝潢族、收納需求者\n- [真蓁嚴選清潔生活館-專賣平板拖把、掃把、掃除用品](https://s.momoshop.com.tw/s/NaHe80dq)：平板拖把怎麼選、掃除工具清單、租屋清潔必備\n- [悅家傢具城](https://s.momoshop.com.tw/s/HnjPEoa8)：商品清單、尺寸動線、使用頻率、收納與送禮情境\n- [RED HOUSE 家具工廠](https://s.momoshop.com.tw/s/5ME3fNxI)：商品清單、尺寸動線、使用頻率、收納與送禮情境\n- [FULTON 富爾頓皇家晴雨傘](https://s.momoshop.com.tw/s/swCkSJDA)：抗風傘比較、通勤傘推薦、旅行雨具、英倫風格配件\n- [S′AIME東京企劃](https://s.momoshop.com.tw/s/fZ9miz2D)：商品清單、尺寸動線、使用頻率、收納與送禮情境\n\n## 導購揭露\n\n本文含品牌／商品導購連結；若你透過部分商品連結前往選購，Elite Fashion 可能取得合作收益。本文仍以編輯判斷與使用情境整理為主，價格、規格、活動與庫存請以商品頁公告為準。\n",
  "authenticityReview": {
    "articleId": "auto-20260621123703-entryway-shoe-cabinet-umbrella-bag-cleaning-tools",
    "slug": "entryway-shoe-cabinet-umbrella-bag-cleaning-tools",
    "riskLevel": "medium",
    "checkedAt": "2026-06-21T12:37:03Z",
    "publishReady": true,
    "claimChecks": [
      {
        "name": "unsupported-source-claim",
        "passed": true,
        "note": "未發現無來源的研究、官方、數據或專家宣稱。"
      },
      {
        "name": "price-stock-claim",
        "passed": true,
        "note": "未發現未佐證的價格、折扣、庫存或排名宣稱。"
      },
      {
        "name": "ymyl-risk",
        "passed": true,
        "note": "未判定為高風險 YMYL 題材。"
      },
      {
        "name": "affiliate-disclosure",
        "passed": true,
        "note": "HTML 含可見導購揭露。"
      },
      {
        "name": "affiliate-rel",
        "passed": true,
        "note": "導購連結皆含 sponsored nofollow。"
      },
      {
        "name": "product-source-url",
        "passed": true,
        "note": "商品資料皆有 sourceProductUrl，或本篇無商品卡。"
      },
      {
        "name": "momo-tracker-status",
        "passed": true,
        "note": "未使用需查證或暫緩的 momo 品牌作為推薦。"
      },
      {
        "name": "editorial-auditor",
        "passed": true,
        "note": "模型校稿未啟用或缺少模型 API key，已完成 deterministic 真實性審核。"
      }
    ],
    "requiredFixes": [],
    "sourceEvidence": [
      "https://www.momoshop.com.tw/TP/TP0005953/main",
      "https://www.momoshop.com.tw/TP/TP0000922/main",
      "https://www.momoshop.com.tw/TP/TP0006481/main",
      "https://www.momoshop.com.tw/TP/TP0007407/main",
      "https://www.momoshop.com.tw/TP/TP0005684/main",
      "https://www.momoshop.com.tw/TP/TP0007070/main",
      "https://s.momoshop.com.tw/s/4sSbnDHc",
      "https://s.momoshop.com.tw/s/NaHe80dq",
      "https://s.momoshop.com.tw/s/HnjPEoa8",
      "https://s.momoshop.com.tw/s/5ME3fNxI",
      "https://s.momoshop.com.tw/s/swCkSJDA",
      "https://s.momoshop.com.tw/s/fZ9miz2D",
      "https://tw.elitefasion.com/lifestyle-culture/entryway-shoe-cabinet-umbrella-bag-cleaning-tools",
      "https://tw.elitefasion.com/images/optimized/article-covers/entryway-shoe-cabinet-umbrella-bag-cleaning-tools.jpg",
      "https://tw.elitefasion.com/feed.xml",
      "https://fonts.googleapis.com",
      "https://fonts.gstatic.com",
      "https://fonts.googleapis.com/css2?family=Playfair+Display:wght@400;500;600;700;800&family=Inter:wght@300;400;500;600;700&display=swap",
      "https://schema.org",
      "https://www.instagram.com/northpath.ca"
    ],
    "reviewer": "automation",
    "editorialAudit": {
      "publishReady": true,
      "summary": "模型校稿未啟用或缺少模型 API key，已完成 deterministic 真實性審核。",
      "checks": [],
      "requiredFixes": [],
      "skipped": true
    }
  }
}
