{
  "title": "一個人住，從空間開始練習獨立：給剛離婚女性的居家安全、收納與節奏設計",
  "slug": "solo-living-home-safety-organization-divorce",
  "excerpt": "剛開始一個人住，家是第一個練習場。這篇文章從安全、動線、收納到睡前儀式，帶妳把空間改造成真正支持自己的地方。",
  "tags": [
    "一人生活",
    "居家安全",
    "收納整理",
    "熟齡離婚",
    "生活節奏"
  ],
  "metaTitle": "一個人住，從空間開始練習獨立：居家安全、收納與節奏設計",
  "metaDescription": "剛離婚、開始一個人住的熟齡女性，如何把家變成安心支持系統？從大門安全、夜間照明、收納動線到睡前儀式，提供可立即執行的空間改造步驟。",
  "category": "lifestyle-culture",
  "series": "中年離婚後的獨立生活指南",
  "audience": "剛離婚或恢復單身、正在學習一個人生活，想把住家改造成支持獨立空間的熟齡女性",
  "readTimeMinutes": 11,
  "listingTitle": "一個人住，從空間開始練習獨立：給剛離婚女性的居家指南",
  "listingExcerpt": "家的樣子，決定妳一個人生活的底氣。從安全、收納到儀式感，打造支持妳的空間。",
  "heroImage": "images/generated/lifestyle/home-sanctuary.png",
  "intro": "恢復單身後，家不只是休息的地方，更是獨立生活最重要的支持系統。這篇文章不談風格，不談昂貴裝潢，而是從台灣常見的公寓、大樓格局出發，帶妳從安全、動線、收納與睡前儀式四個面向，把空間調整成真正為自己服務的狀態，讓「一個人住」成為踏實的享受，而不是孤單的忍受。",
  "sections": [
    {
      "heading": "第一步：安全感先到位，才能談生活品質",
      "paragraphs": [
        "一個人住，最先要處理的不是美感，而是「鎖好門之後，我的心能不能跟著安定下來」。很多女性在離婚後搬進新住處，面對的恐懼不是來自外界，而是空間本身帶來的陌生感。",
        "建議從最基本的硬體開始更新。檢查大門門鎖是否需要更換，特別是前夫或親友曾有備份鑰匙的狀況，換一把電子密碼鎖或指紋鎖，是重新拿回空間主權很具體的儀式。陽台、窗戶的防盜格子或安全鎖也應該一併確認，老舊公寓的後陽台往往是安全死角。",
        "室內可以加裝感應式小夜燈，尤其在從臥室到浴室的動線上。半夜起來不用摸黑找開關，也不會因為一片漆黑而胡思亂想。如果預算允許，門口裝一個可連動手機的電子門眼，能看清楚門外是誰再決定要不要應門，對獨居女性來說是很實用的安心設備。"
      ],
      "bullets": [
        "更換大門鎖或升級電子鎖，清除前夫/他人備用鑰匙。",
        "確認陽台、窗戶安全鎖與防盜設施。",
        "走道與浴室門口加裝感應小夜燈。",
        "考慮安裝電子門眼或視訊門鈴。"
      ]
    },
    {
      "heading": "第二步：動線就是生活效率，別讓空間消耗體力",
      "paragraphs": [
        "一個人住，家務沒有第二雙手分擔，所以動線設計直接影響妳每天的疲勞程度。觀察自己最常重複的動作：早上從起床到出門、晚上從進門到休息，物品放在對的位置，可以省下大量無意識的來回走動。",
        "例如，玄關除了鞋櫃，應該有一個「外出隨手區」：鑰匙、口罩、折疊傘、零錢包固定放在同一個托盤或收納盒裡，避免出門前焦慮尋找。廚房則建議把常用的鍋具、調味料放在伸手可及的下櫃或層架，不要爬高蹲低，保護熟齡後的腰椎與膝蓋。",
        "浴室與洗衣動線也值得重新思考。髒衣籃放在洗澡出來順手的位置，旁邊預留一個空格放待洗衣物袋，週末一次處理。吹風機、保養品集中收納在浴室外的矮櫃或推車上，避免潮濕損壞，也減少在浴室內外穿梭的次數。"
      ],
      "bullets": [
        "玄關設「外出隨手區」，固定放置鑰匙、口罩、錢包。",
        "廚房常用物品收在腰部高度的抽屜或層架。",
        "浴室到洗衣區的髒衣動線要順手一氣呵成。",
        "吹風機與保養品移到浴室外的乾燥區域。"
      ]
    },
    {
      "heading": "第三步：收納不是把東西藏起來，而是讓生活被支持",
      "paragraphs": [
        "剛離婚的階段，家裡可能混雜著從舊家打包來的箱子、暫時塞進櫃子的雜物，還有不知道該不該留的紀念品。這時候的收納重點不是「整齊」，而是「分類與放手」。",
        "可以先從三個分類開始：每日必需品、偶爾使用品、正在猶豫該不該留的物品。每日必需品優先給它最好的位置，例如常穿的幾套衣服掛在衣櫃最外側，常讀的書放在沙發旁的小邊桌。偶爾使用的換季衣物、行李箱、備品，收進儲藏室或高處收納箱，明確貼上標籤。",
        "至於那些「不知道該不該留」的東西——前夫的物品、舊照片、婚禮紀念物，不用急著馬上決定。給自己一個緩衝箱，設定三個月或半年的期限。時間到了如果還是沒有勇氣打開，或許那已經說明答案了。收納的過程，其實也是在整理心裡的位置。"
      ],
      "bullets": [
        "將物品分成「每日必用」、「偶爾使用」、「猶豫中」三類。",
        "每日必需品給最順手的位置，不必藏起來。",
        "準備一個「緩衝箱」，給需要時間決定的紀念物。",
        "收納標籤明確，減少翻找時的焦慮感。"
      ]
    },
    {
      "heading": "第四步：建立專屬的夜間儀式，把空間轉換成休息模式",
      "paragraphs": [
        "白天可以忙碌、可以專注，但夜晚一個人回到安靜的家，才是孤獨感最容易浮現的時刻。與其對抗它，不如用一套固定的夜間儀式，主動把空間轉換成「休息模式」。",
        "儀式不需要複雜。例如：晚餐後把客廳主燈關掉，只留一盞黃光的立燈或桌燈，搭配固定的音樂清單或 Podcast。接著花十分鐘簡單整理檯面，把用過的杯子洗好、沙發的抱枕拍鬆。最後泡一杯無咖啡因的花草茶，在固定的角落坐下來閱讀或寫日記。",
        "這些重複的小動作，會讓大腦逐漸學習到：當這些事情發生時，就是該放鬆的時候了。空間也因此不再只是空蕩的房間，而是被妳的節奏填滿的、有生命力的場域。週末可以加入泡澡、點香氛蠟燭或換床單的步驟，讓這個「一個人的家」擁有專屬於妳的味道與觸感。"
      ],
      "bullets": [
        "設定固定時間切換光線，從主燈改為溫暖的間接照明。",
        "建立十分鐘的睡前整理儀式，讓空間恢復秩序。",
        "準備一杯熱飲與固定閱讀角落，作為休息的信號。",
        "週末加入香氛、泡澡或更換寢具，強化舒適感。"
      ]
    }
  ],
  "faq": [
    {
      "question": "一個人住，如何克服晚上睡覺時的恐懼感？",
      "answer": "先從硬體安全做起，確認門窗鎖好、加裝感應夜燈和電子門眼會帶來很大的安心感。心理上，可以建立一套睡前儀式，例如固定聽某個溫柔的 Podcast、點一盞習慣的小燈，讓大腦把「這些事」和「安全放鬆」連結在一起，漸漸取代對黑暗的恐懼。"
    },
    {
      "question": "離婚後搬進比較小的房子，東西放不下該怎麼辦？",
      "answer": "小空間更需要精準分類。優先留下每日真正會用到的物品，善用垂直收納與多功能家具（例如可收納的茶几、掀床）。那些「可能以後會用到」或帶有沉重回憶的物品，可以先放進緩衝箱，給自己一段心理整理期後再決定去留，不要讓物品擠壓了妳當下的生活空間。"
    }
  ],
  "extendedReading": [
    {
      "title": "離婚後先做哪 6 件事：重整生活秩序的可執行清單",
      "url": "/lifestyle-culture/post-divorce-first-6-steps.html"
    },
    {
      "title": "瀏覽更多生活品味文章",
      "url": "/lifestyle-culture.html"
    }
  ],
  "cta": {
    "label": "瀏覽更多生活品味文章",
    "url": "/lifestyle-culture.html",
    "text": "從空間開始，一步步拿回生活的主導權。看完這篇後，也可以回到生活品味分類，繼續閱讀這個主題的後續文章。"
  },
  "id": "auto-20260425172236-solo-living-home-safety-organization-divorce",
  "queueId": "Q-0001",
  "publishedAt": "2026-04-25T17:22:36Z",
  "publishedDateText": "2026年4月25日",
  "url": "https://tw.elitefasion.com/lifestyle-culture/solo-living-home-safety-organization-divorce.html",
  "file": "lifestyle-culture/solo-living-home-safety-organization-divorce.html",
  "relativeUrl": "lifestyle-culture/solo-living-home-safety-organization-divorce.html",
  "status": "published",
  "markdownBody": "# 一個人住，從空間開始練習獨立：給剛離婚女性的居家安全、收納與節奏設計\n\n恢復單身後，家不只是休息的地方，更是獨立生活最重要的支持系統。這篇文章不談風格，不談昂貴裝潢，而是從台灣常見的公寓、大樓格局出發，帶妳從安全、動線、收納與睡前儀式四個面向，把空間調整成真正為自己服務的狀態，讓「一個人住」成為踏實的享受，而不是孤單的忍受。\n\n## 第一步：安全感先到位，才能談生活品質\n\n一個人住，最先要處理的不是美感，而是「鎖好門之後，我的心能不能跟著安定下來」。很多女性在離婚後搬進新住處，面對的恐懼不是來自外界，而是空間本身帶來的陌生感。\n\n建議從最基本的硬體開始更新。檢查大門門鎖是否需要更換，特別是前夫或親友曾有備份鑰匙的狀況，換一把電子密碼鎖或指紋鎖，是重新拿回空間主權很具體的儀式。陽台、窗戶的防盜格子或安全鎖也應該一併確認，老舊公寓的後陽台往往是安全死角。\n\n室內可以加裝感應式小夜燈，尤其在從臥室到浴室的動線上。半夜起來不用摸黑找開關，也不會因為一片漆黑而胡思亂想。如果預算允許，門口裝一個可連動手機的電子門眼，能看清楚門外是誰再決定要不要應門，對獨居女性來說是很實用的安心設備。\n\n- 更換大門鎖或升級電子鎖，清除前夫/他人備用鑰匙。\n- 確認陽台、窗戶安全鎖與防盜設施。\n- 走道與浴室門口加裝感應小夜燈。\n- 考慮安裝電子門眼或視訊門鈴。\n\n## 第二步：動線就是生活效率，別讓空間消耗體力\n\n一個人住，家務沒有第二雙手分擔，所以動線設計直接影響妳每天的疲勞程度。觀察自己最常重複的動作：早上從起床到出門、晚上從進門到休息，物品放在對的位置，可以省下大量無意識的來回走動。\n\n例如，玄關除了鞋櫃，應該有一個「外出隨手區」：鑰匙、口罩、折疊傘、零錢包固定放在同一個托盤或收納盒裡，避免出門前焦慮尋找。廚房則建議把常用的鍋具、調味料放在伸手可及的下櫃或層架，不要爬高蹲低，保護熟齡後的腰椎與膝蓋。\n\n浴室與洗衣動線也值得重新思考。髒衣籃放在洗澡出來順手的位置，旁邊預留一個空格放待洗衣物袋，週末一次處理。吹風機、保養品集中收納在浴室外的矮櫃或推車上，避免潮濕損壞，也減少在浴室內外穿梭的次數。\n\n- 玄關設「外出隨手區」，固定放置鑰匙、口罩、錢包。\n- 廚房常用物品收在腰部高度的抽屜或層架。\n- 浴室到洗衣區的髒衣動線要順手一氣呵成。\n- 吹風機與保養品移到浴室外的乾燥區域。\n\n## 第三步：收納不是把東西藏起來，而是讓生活被支持\n\n剛離婚的階段，家裡可能混雜著從舊家打包來的箱子、暫時塞進櫃子的雜物，還有不知道該不該留的紀念品。這時候的收納重點不是「整齊」，而是「分類與放手」。\n\n可以先從三個分類開始：每日必需品、偶爾使用品、正在猶豫該不該留的物品。每日必需品優先給它最好的位置，例如常穿的幾套衣服掛在衣櫃最外側，常讀的書放在沙發旁的小邊桌。偶爾使用的換季衣物、行李箱、備品，收進儲藏室或高處收納箱，明確貼上標籤。\n\n至於那些「不知道該不該留」的東西——前夫的物品、舊照片、婚禮紀念物，不用急著馬上決定。給自己一個緩衝箱，設定三個月或半年的期限。時間到了如果還是沒有勇氣打開，或許那已經說明答案了。收納的過程，其實也是在整理心裡的位置。\n\n- 將物品分成「每日必用」、「偶爾使用」、「猶豫中」三類。\n- 每日必需品給最順手的位置，不必藏起來。\n- 準備一個「緩衝箱」，給需要時間決定的紀念物。\n- 收納標籤明確，減少翻找時的焦慮感。\n\n## 第四步：建立專屬的夜間儀式，把空間轉換成休息模式\n\n白天可以忙碌、可以專注，但夜晚一個人回到安靜的家，才是孤獨感最容易浮現的時刻。與其對抗它，不如用一套固定的夜間儀式，主動把空間轉換成「休息模式」。\n\n儀式不需要複雜。例如：晚餐後把客廳主燈關掉，只留一盞黃光的立燈或桌燈，搭配固定的音樂清單或 Podcast。接著花十分鐘簡單整理檯面，把用過的杯子洗好、沙發的抱枕拍鬆。最後泡一杯無咖啡因的花草茶，在固定的角落坐下來閱讀或寫日記。\n\n這些重複的小動作，會讓大腦逐漸學習到：當這些事情發生時，就是該放鬆的時候了。空間也因此不再只是空蕩的房間，而是被妳的節奏填滿的、有生命力的場域。週末可以加入泡澡、點香氛蠟燭或換床單的步驟，讓這個「一個人的家」擁有專屬於妳的味道與觸感。\n\n- 設定固定時間切換光線，從主燈改為溫暖的間接照明。\n- 建立十分鐘的睡前整理儀式，讓空間恢復秩序。\n- 準備一杯熱飲與固定閱讀角落，作為休息的信號。\n- 週末加入香氛、泡澡或更換寢具，強化舒適感。\n\n## FAQ\n\n### 一個人住，如何克服晚上睡覺時的恐懼感？\n\n先從硬體安全做起，確認門窗鎖好、加裝感應夜燈和電子門眼會帶來很大的安心感。心理上，可以建立一套睡前儀式，例如固定聽某個溫柔的 Podcast、點一盞習慣的小燈，讓大腦把「這些事」和「安全放鬆」連結在一起，漸漸取代對黑暗的恐懼。\n\n### 離婚後搬進比較小的房子，東西放不下該怎麼辦？\n\n小空間更需要精準分類。優先留下每日真正會用到的物品，善用垂直收納與多功能家具（例如可收納的茶几、掀床）。那些「可能以後會用到」或帶有沉重回憶的物品，可以先放進緩衝箱，給自己一段心理整理期後再決定去留，不要讓物品擠壓了妳當下的生活空間。\n\n## 延伸閱讀\n\n- [離婚後先做哪 6 件事：重整生活秩序的可執行清單](/lifestyle-culture/離婚後先做哪-6-件事-重整生活秩序的.html)\n- [瀏覽更多生活品味文章](/lifestyle-culture.html)\n\n## CTA\n\n從空間開始，一步步拿回生活的主導權。延伸閱讀完整系列文章，陪妳走過這段重整的旅程。\n\n[閱讀更多獨立生活指南](/lifestyle-culture/series/中年離婚後的獨立生活指南)\n"
}
